smartestio/__init__.py
smartestio/core.py
smartestio-0.1.0.dist-info/licenses/LICENSE
smartestio-0.1.0.dist-info/METADATA
smartestio-0.1.0.dist-info/WHEEL
smartestio-0.1.0.dist-info/top_level.txt
smartestio-0.1.0.dist-info/RECORD
